stltovoxel/__init__.py
stltovoxel/__main__.py
stltovoxel/convert.py
stltovoxel/perimeter.py
stltovoxel/polygon_repair.py
stltovoxel/slice.py
stl_to_voxel-0.10.1.dist-info/LICENCE.md
stl_to_voxel-0.10.1.dist-info/METADATA
stl_to_voxel-0.10.1.dist-info/WHEEL
stl_to_voxel-0.10.1.dist-info/entry_points.txt
stl_to_voxel-0.10.1.dist-info/RECORD
