Metadata-Version: 2.3
Name: stl-to-voxel
Version: 0.10.1
Summary: Turn STL files into voxels, images, and videos
License: MIT
Author: Christian Pederkoff
Requires-Python: >=3.9
Classifier: Programming Language :: Python
Classifier: Programming Language :: Python :: 3
Classifier: Topic :: Software Development :: Libraries :: Python Modules
Provides-Extra: dev
Requires-Dist: Pillow (>=10.0.1)
Requires-Dist: black (>=25.0) ; extra == "dev"
Requires-Dist: flake8 (>=5.0.4) ; extra == "dev"
Requires-Dist: isort (>=6.0) ; extra == "dev"
Requires-Dist: numpy (>=1.13)
Requires-Dist: numpy-stl (>=2.17)
Requires-Dist: pep8-naming (>=0.13.2) ; extra == "dev"
Requires-Dist: pytest (>=8.0) ; extra == "dev"
Project-URL: Bug Tracker, https://github.com/cpederkoff/stl-to-voxel/issues
Project-URL: Documentation, https://github.com/cpederkoff/stl-to-voxel/wiki
Project-URL: Repository, https://github.com/cpederkoff/stl-to-voxel
